pycrobe/__init__.py
pycrobe/objects.py
pycrobe-0.1.5.dist-info/DESCRIPTION.rst
pycrobe-0.1.5.dist-info/METADATA
pycrobe-0.1.5.dist-info/RECORD
pycrobe-0.1.5.dist-info/WHEEL
pycrobe-0.1.5.dist-info/metadata.json
pycrobe-0.1.5.dist-info/top_level.txt
