Metadata-Version: 2.0
Name: pycrobe
Version: 0.1.5
Summary: A simple package for simulations of microbial growth experiments with realistic sources of error.
Home-page: https://github.com/ryansmcgee/pycrobe
Author: Ryan Seamus McGee
Author-email: ryansmcgee@gmail.com
License: MIT
Platform: UNKNOWN
